ckanext_data_qld-3.0.1-py3.9-nspkg.pth
ckanext/data_qld/__init__.py
ckanext/data_qld/actions.py
ckanext/data_qld/auth_functions.py
ckanext/data_qld/blueprints.py
ckanext/data_qld/click_cli.py
ckanext/data_qld/command_functions.py
ckanext/data_qld/commands.py
ckanext/data_qld/constants.py
ckanext/data_qld/controller.py
ckanext/data_qld/controller_functions.py
ckanext/data_qld/converters.py
ckanext/data_qld/datarequest_auth_functions.py
ckanext/data_qld/flask_plugin.py
ckanext/data_qld/helpers.py
ckanext/data_qld/plugin.py
ckanext/data_qld/pylons_plugin.py
ckanext/data_qld/validation.py
ckanext/data_qld/dataset_deletion/__init__.py
ckanext/data_qld/dataset_deletion/helpers.py
ckanext/data_qld/de_identified_data/__init__.py
ckanext/data_qld/de_identified_data/helpers.py
ckanext/data_qld/google_analytics/__init__.py
ckanext/data_qld/google_analytics/controller.py
ckanext/data_qld/google_analytics/plugin.py
ckanext/data_qld/reporting/__init__.py
ckanext/data_qld/reporting/blueprints.py
ckanext/data_qld/reporting/constants.py
ckanext/data_qld/reporting/controller.py
ckanext/data_qld/reporting/controller_functions.py
ckanext/data_qld/reporting/helpers/__init__.py
ckanext/data_qld/reporting/helpers/export_helpers.py
ckanext/data_qld/reporting/helpers/helpers.py
ckanext/data_qld/reporting/logic/__init__.py
ckanext/data_qld/reporting/logic/action/__init__.py
ckanext/data_qld/reporting/logic/action/get.py
ckanext/data_qld/resource_freshness/__init__.py
ckanext/data_qld/resource_freshness/commands.py
ckanext/data_qld/resource_freshness/validation.py
ckanext/data_qld/resource_freshness/helpers/__init__.py
ckanext/data_qld/resource_freshness/helpers/helpers.py
ckanext/data_qld/resource_freshness/logic/__init__.py
ckanext/data_qld/resource_freshness/logic/actions/__init__.py
ckanext/data_qld/resource_freshness/logic/actions/get.py
ckanext/data_qld/resource_visibility/__init__.py
ckanext/data_qld/resource_visibility/helpers.py
ckanext/data_qld/resource_visibility/validators.py
ckanext_data_qld-3.0.1.dist-info/LICENSE
ckanext_data_qld-3.0.1.dist-info/METADATA
ckanext_data_qld-3.0.1.dist-info/WHEEL
ckanext_data_qld-3.0.1.dist-info/entry_points.txt
ckanext_data_qld-3.0.1.dist-info/namespace_packages.txt
ckanext_data_qld-3.0.1.dist-info/top_level.txt
ckanext_data_qld-3.0.1.dist-info/RECORD
